[
  {
    "DeniedAlternatives": [],
    "Files": {
      "items/materials/retexredsandstone.matitem": [
        "/glitchdescription/glitchEmotedText"
      ],
      "items/materials/retexsandstone.matitem": [
        "/glitchdescription/glitchEmotedText"
      ],
      "tiles/materials/retexsandstone01.material": [
        "/glitchDescription/glitchEmotedText"
      ]
    },
    "Texts": {
      "Eng": "Sandstone."
    }
  },
  {
    "DeniedAlternatives": [],
    "Files": {
      "items/materials/retexredsandstone.matitem": [
        "/florandescription"
      ],
      "items/materials/retexsandstone.matitem": [
        "/florandescription"
      ],
      "tiles/materials/retexredsandstone.material": [
        "/floranDescription"
      ],
      "tiles/materials/retexsandstone01.material": [
        "/floranDescription"
      ]
    },
    "Texts": {
      "Eng": "Sssandstone."
    }
  },
  {
    "DeniedAlternatives": [],
    "Files": {
      "items/materials/retexredsandstone.matitem": [
        "/description"
      ],
      "items/materials/retexsandstone.matitem": [
        "/description"
      ],
      "tiles/materials/retexsandstone01.material": [
        "/description"
      ]
    },
    "Texts": {
      "Eng": "Tough sandstone."
    }
  }
]