[
  {
    "DeniedAlternatives": [],
    "Files": {
      "items/armors/fupioneerarmor/fupioneer.chest": [
        "/description"
      ]
    },
    "Texts": {
      "Chs": "这件装备将带你进入一个新的世界。",
      "Eng": "A chestguard protects the pioneer's first steps into a new world."
    }
  },
  {
    "DeniedAlternatives": [],
    "Files": {
      "items/armors/fupioneerarmor/fupioneer.chest": [
        "/shortdescription"
      ]
    },
    "Texts": {
      "Chs": "流浪者胸甲",
      "Eng": "Wanderer Chestguard"
    }
  }
]