[
  {
    "DeniedAlternatives": [],
    "Files": {
      "objects/avaligeneric/racks/avaligundisplay1.object": [
        "/description"
      ],
      "objects/avaligeneric/racks/avaligundisplay2.object": [
        "/description"
      ]
    },
    "Texts": {
      "Eng": "An Avali assault rifle, all set for display."
    }
  },
  {
    "DeniedAlternatives": [],
    "Files": {
      "objects/avaligeneric/racks/avaligundisplay1.object": [
        "/apexDescription"
      ],
      "objects/avaligeneric/racks/avaligundisplay2.object": [
        "/apexDescription"
      ]
    },
    "Texts": {
      "Eng": "Fascinating! It appears the Avali have man-portable rail weapons."
    }
  },
  {
    "DeniedAlternatives": [],
    "Files": {
      "objects/avaligeneric/racks/avaligundisplay1.object": [
        "/humanDescription"
      ],
      "objects/avaligeneric/racks/avaligundisplay2.object": [
        "/humanDescription"
      ]
    },
    "Texts": {
      "Eng": "It looks like a railgun, but way too small. Maybe it's a toy for kids to play with?"
    }
  },
  {
    "DeniedAlternatives": [],
    "Files": {
      "objects/avaligeneric/racks/avaligundisplay1.object": [
        "/avaliDescription"
      ],
      "objects/avaligeneric/racks/avaligundisplay2.object": [
        "/avaliDescription"
      ]
    },
    "Texts": {
      "Eng": "Our railguns have user recognition grips, only recognised users of this gun can fire it."
    }
  },
  {
    "DeniedAlternatives": [],
    "Files": {
      "objects/avaligeneric/racks/avaligundisplay1.object": [
        "/glitchDescription/glitchEmotedText"
      ],
      "objects/avaligeneric/racks/avaligundisplay2.object": [
        "/glitchDescription/glitchEmotedText"
      ]
    },
    "Texts": {
      "Eng": "This device appears to have 2 separated metal rails connected to a high voltage power source."
    }
  }
]