[
  {
    "DeniedAlternatives": [],
    "Files": {
      "quests/stations/designlab/fuquest_mutavisk.questtemplate": [
        "/completionText"
      ]
    },
    "Texts": {
      "Chs": "现在，你可以凭借你的基础知识，想必已经种植出了一大堆有用的植物。每种植物都会为你提供不一样的好处，所以调整你的种植计划以迎合你的需求吧！",
      "Eng": "Now that you know the basics, you should be able to whip up a wide array of useful plants. Each provides different benefits, so tailor your farm to your personal needs!"
    }
  },
  {
    "DeniedAlternatives": [],
    "Files": {
      "quests/stations/designlab/fuquest_mutavisk.questtemplate": [
        "/text"
      ]
    },
    "Texts": {
      "Chs": "^orange;飞螳种子^reset;是极其重要的作物，因为在宇宙中独一无二的^orange;飞螳丝^reset;就是飞螳种子产出的。所以为什么不快点去尝试制造一些飞螳种子呢？",
      "Eng": "The ^orange;Mutavisk^reset; seed is extremely useful, being the sole source in the galaxy of the wonderous textile known as ^orange;Mutavisk Silk^reset;. Why not try crafting a few seeds?"
    }
  },
  {
    "DeniedAlternatives": [],
    "Files": {
      "quests/stations/designlab/fuquest_mutavisk.questtemplate": [
        "/title"
      ]
    },
    "Texts": {
      "Chs": "^cyan;高级织物",
      "Eng": "^cyan;Advanced Textiles"
    }
  }
]