[
  {
    "DeniedAlternatives": [],
    "Files": {
      "objects/avaligeneric/kitchen/avalikitchencupboard.object": [
        "/description"
      ]
    },
    "Texts": {
      "Eng": "A hi-tech cupboard for hi-tech goodies."
    }
  },
  {
    "DeniedAlternatives": [],
    "Files": {
      "objects/avaligeneric/kitchen/avalikitchencupboard.object": [
        "/shortdescription"
      ]
    },
    "Texts": {
      "Eng": "Hi-Tech Cupboard"
    }
  },
  {
    "DeniedAlternatives": [],
    "Files": {
      "objects/avaligeneric/kitchen/avalikitchencupboard.object": [
        "/humanDescription"
      ]
    },
    "Texts": {
      "Eng": "It's a cupboard, could probably get something similar at OKEA."
    }
  },
  {
    "DeniedAlternatives": [],
    "Files": {
      "objects/avaligeneric/kitchen/avalikitchencupboard.object": [
        "/glitchDescription/glitchEmotedText"
      ]
    },
    "Texts": {
      "Eng": "Once you have seen one cupboard you have seen them all."
    }
  },
  {
    "DeniedAlternatives": [],
    "Files": {
      "objects/avaligeneric/kitchen/avalikitchencupboard.object": [
        "/hylotlDescription"
      ]
    },
    "Texts": {
      "Eng": "Such soulless designs make me long for home."
    }
  },
  {
    "DeniedAlternatives": [],
    "Files": {
      "objects/avaligeneric/kitchen/avalikitchencupboard.object": [
        "/apexDescription"
      ]
    },
    "Texts": {
      "Eng": "This cupboard is remarkably light yet sturdy."
    }
  },
  {
    "DeniedAlternatives": [],
    "Files": {
      "objects/avaligeneric/kitchen/avalikitchencupboard.object": [
        "/avianDescription"
      ]
    },
    "Texts": {
      "Eng": "This'd make a fantastic trophy cabinet."
    }
  },
  {
    "DeniedAlternatives": [],
    "Files": {
      "objects/avaligeneric/kitchen/avalikitchencupboard.object": [
        "/avaliDescription"
      ]
    },
    "Texts": {
      "Eng": "To the naked eye these look a bit boring, but that is just to maximise the versatility of augmented reality."
    }
  },
  {
    "DeniedAlternatives": [],
    "Files": {
      "objects/avaligeneric/kitchen/avalikitchencupboard.object": [
        "/floranDescription"
      ]
    },
    "Texts": {
      "Eng": "What good isss a box to hide things in, if you can sssee through it?"
    }
  }
]